trdb2py/__init__.py
trdb2py/assetsutils.py
trdb2py/candlesutils.py
trdb2py/config.py
trdb2py/config_test.py
trdb2py/indicator.py
trdb2py/indicator_test.py
trdb2py/pdutils.py
trdb2py/pdutils_test.py
trdb2py/plotly.py
trdb2py/statistics.py
trdb2py/timeutils.py
trdb2py/timeutils_test.py
trdb2py/trading2_pb2.py
trdb2py/trading2_pb2_grpc.py
trdb2py/tradingdb2_pb2.py
trdb2py/tradingdb2_pb2_grpc.py
trdb2py/tradingnode2_pb2.py
trdb2py/tradingnode2_pb2_grpc.py
trdb2py/trdb2.py
trdb2py/trdb2_test.py
trdb2py/trdb2chatbot_pb2.py
trdb2py/trdb2chatbot_pb2_grpc.py
trdb2py/trdb2utils.py
trdb2py/utils.py
trdb2py/utils_test.py
trdb2py-0.3.27.dist-info/LICENSE
trdb2py-0.3.27.dist-info/METADATA
trdb2py-0.3.27.dist-info/WHEEL
trdb2py-0.3.27.dist-info/entry_points.txt
trdb2py-0.3.27.dist-info/top_level.txt
trdb2py-0.3.27.dist-info/RECORD
