Metadata-Version: 2.1
Name: trdb2py
Version: 0.3.27
Summary: tradingdb2 for python
Home-page: https://github.com/zhs007/trdb2py
Author: Zerro Zhao
Author-email: zerrozhao@gmail.com
License: UNKNOWN
Platform: UNKNOWN
Classifier: Programming Language :: Python :: 3
Classifier: Operating System :: Microsoft :: Windows
Classifier: Operating System :: POSIX
Classifier: Operating System :: Unix
Classifier: Operating System :: MacOS
